[
  {
    "name"  : "Ana",
    "shortnama" : "jm",
    "reknown" : "Inno Live",
    "bio"   : "hello world"
  },
  {
    "name"  : "Juan",
    "shortname" : "jm",
    "reknown" : "tatata",
    "bio"   : "hello world"
  },
  {
    "name"  : "Beba",
    "shortname" : "jm",
    "reknown" : "Inno Live",
    "bio"   : "hello world"
  },
  {
    "name"  : "Alex",
    "shortname" : "jm",
    "reknown" : "tatata",
    "bio"   : "hello world"
  },
    {
    "name"  : "Gio",
    "shortname" : "jm",
    "reknown" : "Inno Live",
    "bio"   : "hello world"
  },
  {
    "name"  : "Danny",
    "shortname" : "jm",
    "reknown" : "tatata",
    "bio"   : "hello world"
  },
  {
    "name"  : "Jose",
    "shortname" : "jm",
    "reknown" : "Inno Live",
    "bio"   : "hello world"
  }
]